{
  "286607198854053890": {
    "profile_id": "2583713",
    "name": "Desconocido"
  },
  "697996987210924072": {
    "profile_id": "2304739",
    "name": "Desconocido"
  },
  "238414625417330688": {
    "profile_id": "1780624",
    "name": "Desconocido"
  },
  "244547091362217984": {
    "profile_id": "15605540",
    "name": "Desconocido"
  },
  "326046458673365002": {
    "profile_id": "11033804",
    "name": "Desconocido"
  },
  "959267535524606022": {
    "profile_id": "5627235",
    "name": "Desconocido"
  },
  "335286995486244867": {
    "profile_id": "2393008",
    "name": "Desconocido"
  },
  "662427737138528308": {
    "profile_id": "14501687",
    "name": "Desconocido"
  },
  "485610092092456975": {
    "profile_id": "828458",
    "name": "Desconocido"
  },
  "277256502023290881": {
    "profile_id": "5204719",
    "name": "Desconocido"
  },
  "689907393001291884": {
    "profile_id": "5736044",
    "name": "Desconocido"
  },
  "697973693157998712": {
    "profile_id": "1465372",
    "name": "Desconocido"
  },
  "724668688145580062": {
    "profile_id": "2899006",
    "name": "Desconocido"
  },
  "1007049335315374242": {
    "profile_id": "19186614",
    "name": "Desconocido"
  },
  "442189398667296788": {
    "profile_id": "4465309",
    "name": "Desconocido"
  },
  "341001672786575360": {
    "profile_id": "673060",
    "name": "Desconocido"
  },
  "219641963371036672": {
    "profile_id": "11546855",
    "name": "Desconocido"
  },
  "750789709252395108": {
    "profile_id": "3528971",
    "name": "Desconocido"
  },
  "709904591453683766": {
    "profile_id": "476764",
    "name": "Desconocido"
  },
  "582941701518262412": {
    "profile_id": "14779963",
    "name": "Desconocido"
  },
  "833806737902534738": {
    "profile_id": "2639502",
    "name": "Desconocido"
  },
  "347539956605911041": {
    "profile_id": "233173",
    "name": "Desconocido"
  },
  "580229190645972994": {
    "profile_id": "3068482",
    "name": "Desconocido"
  },
  "701537224248000563": {
    "profile_id": "2317043",
    "name": "Desconocido"
  },
  "590693837509361902": {
    "profile_id": "9097311",
    "name": "Desconocido"
  },
  "135113382217908224": {
    "profile_id": "2878364",
    "name": "Desconocido"
  },
  "757033857362165792": {
    "profile_id": "2890463",
    "name": "Desconocido"
  },
  "1244725529093869687": {
    "profile_id": "19764836",
    "name": "Desconocido"
  },
  "369911696023879681": {
    "profile_id": "18148390",
    "name": "Desconocido"
  },
  "846515810381987860": {
    "profile_id": "4752684",
    "name": "Desconocido"
  },
  "952599207410303016": {
    "profile_id": "17358692",
    "name": "Desconocido"
  },
  "425297928610119692": {
    "profile_id": "1464680",
    "name": "Desconocido"
  },
  "481154599881932811": {
    "profile_id": "199325",
    "name": "Desconocido"
  },
  "524738089252552716": {
    "profile_id": "2609789",
    "name": "Desconocido"
  },
  "1008090545513570495": {
    "profile_id": "10473376",
    "name": "Desconocido"
  },
  "249400646782943235": {
    "profile_id": "1795290",
    "name": "Desconocido"
  },
  "342830926142767115": {
    "profile_id": "2213230",
    "name": "Desconocido"
  },
  "427965323799691284": {
    "profile_id": "9864299",
    "name": "Desconocido"
  },
  "694749732467245088": {
    "profile_id": "2213923",
    "name": "Desconocido"
  },
  "755853346149105786": {
    "profile_id": "10222046",
    "name": "Desconocido"
  },
  "395418630202064907": {
    "profile_id": "2449039",
    "name": "Desconocido"
  },
  "851950857146466336": {
    "profile_id": "6044259",
    "name": "Desconocido"
  },
  "121771867198455808": {
    "profile_id": "6239045",
    "name": "Desconocido"
  },
  "852387609916211270": {
    "profile_id": "1825664",
    "name": "Desconocido"
  },
  "709879345346248785": {
    "profile_id": "2582641",
    "name": "Desconocido"
  },
  "1293646842625785968": {
    "profile_id": "17272260",
    "name": "Desconocido"
  },
  "465307831583637514": {
    "profile_id": "19032038",
    "name": "Desconocido"
  },
  "425899279962341377": {
    "profile_id": "583716",
    "name": "Desconocido"
  },
  "896216989922635777": {
    "profile_id": "8921754",
    "name": "Desconocido"
  },
  "207643066855718923": {
    "profile_id": "17467929",
    "name": "Desconocido"
  },
  "603065873133207562": {
    "profile_id": "2785622",
    "name": "Desconocido"
  },
  "221364761613303808": {
    "profile_id": "22874187",
    "name": "Desconocido"
  }
}